cloey/__init__.py
cloey/connection.py
cloey/database.py
cloey/orm.py
cloey/_constants/__init__.py
cloey/_utils/__init__.py
cloey/_utils/crud.py
cloey/_utils/logger.py
cloey/_utils/migrations.py
cloey/_utils/relationships.py
cloey_orm-0.0.7.dist-info/METADATA
cloey_orm-0.0.7.dist-info/WHEEL
cloey_orm-0.0.7.dist-info/top_level.txt
cloey_orm-0.0.7.dist-info/RECORD
