Metadata-Version: 2.4
Name: cloey-orm
Version: 0.0.7
Summary: The Python ORM for PostgreSQL
Author: Xindiri Inc.
Author-email: info@xindiri.com
Classifier: Programming Language :: Python :: 3
Classifier: License :: OSI Approved :: MIT License
Classifier: Operating System :: OS Independent
Requires-Python: >=3.6
Requires-Dist: psycopg2-binary
Dynamic: author
Dynamic: author-email
Dynamic: classifier
Dynamic: description
Dynamic: description-content-type
Dynamic: requires-dist
Dynamic: requires-python
Dynamic: summary
